<Language Name="Deutsch" IsDefault="true" IsRightToLeft="false">
	<LocaleResource Name="Plugins.FriendlyName.SmartStore.FacebookAuth" AppendRootKey="false">
		<Value>Facebook Login</Value>
	</LocaleResource>
	<LocaleResource Name="AdminInstruction">
		<Value>
			<![CDATA[<p>So richten Sie die Facebook Authentifizierungen ein:</p><ul>
	<li>Erstellen Sie bei Facebook eine neue App vom Typ <b>Facebook Login</b>. Deren Zugangsdaten tragen Sie bitte unten in das Formular ein.</li>
	<li>Unter <b>Facebook Login &gt; Einstellungen &gt; Gültige OAuth Redirect URIs</b> wird die unten aufgeführte URL eingetragen.</li>
	<li>Aktivieren Sie in den Kundeneinstellungen des Shops die automatische Registrierung, falls extern autorisierte Besucher automatisch registriert werden sollen.</li>
	</ul>]]>
		</Value>
	</LocaleResource>
	<LocaleResource Name="Login">
		<Value>Mit Facebook anmelden</Value>
	</LocaleResource>
	<LocaleResource Name="ClientKeyIdentifier">
		<Value>Benutzer-Schlüssel-Identifikator (App ID)</Value>
	</LocaleResource>
	<LocaleResource Name="ClientKeyIdentifier.Hint">
		<Value>Geben Sie hier Ihren Benutzer-Schlüssel-Identifikator (App ID) an.</Value>
	</LocaleResource>
	<LocaleResource Name="ClientSecret">
		<Value>Benutzer-Sicherheitsschlüssel (App Secret)</Value>
	</LocaleResource>
	<LocaleResource Name="ClientSecret.Hint">
		<Value>Geben Sie hier Ihren Benutzer-Sicherheitsschlüssel (App Secret) an.</Value>
	</LocaleResource>
	<LocaleResource Name="RedirectUri">
		<Value>Weiterleitungs URL (OAuth Redirect URI)</Value>
	</LocaleResource>
	<LocaleResource Name="RedirectUri.Hint">
		<Value>Die bei Facebook einzutragende Weiterleitungs URL (OAuth Redirect URI).</Value>
	</LocaleResource>
</Language>